rapidai/__init__.py
rapidai/_modidx.py
rapidai/accel.py
rapidai/activations.py
rapidai/augment.py
rapidai/conv.py
rapidai/core.py
rapidai/datasets.py
rapidai/diffusion.py
rapidai/fid.py
rapidai/imports.py
rapidai/init.py
rapidai/learner.py
rapidai/resnet.py
rapidai/sgd.py
rapidai/training.py
rapidai/utils.py
rapidai-0.0.9.dist-info/LICENSE
rapidai-0.0.9.dist-info/METADATA
rapidai-0.0.9.dist-info/WHEEL
rapidai-0.0.9.dist-info/entry_points.txt
rapidai-0.0.9.dist-info/top_level.txt
rapidai-0.0.9.dist-info/RECORD
